[
  {
    "index": 1,
    "dataset": "pubmed",
    "backbone": "gat",
    "stage": "stage1",
    "result_name": "pubmed_gat_frontdoor_stage1_lr0.01_weight_decay5e-05_dropout0.1_hidden_channels32_K2",
    "log_file": "search_logs_frontdoor/pubmed/gat/stage1/001_pubmed_gat_frontdoor_stage1_lr0.01_weight_decay5e-05_dropout0.1_hidden_channels32_K2.log",
    "command": "python main_frontdoor.py --dataset pubmed --backbone_type gat --store_result --epochs 500 --runs 2 --num_layers 2 --device 1 --combine_result --lr 0.01 --weight_decay 5e-05 --dropout 0.1 --hidden_channels 32 --K 2 --result_name pubmed_gat_frontdoor_stage1_lr0.01_weight_decay5e-05_dropout0.1_hidden_channels32_K2",
    "return_code": 0,
    "elapsed_seconds": 376.94,
    "lr": 0.01,
    "weight_decay": 5e-05,
    "dropout": 0.1,
    "hidden_channels": 32,
    "K": 2,
    "highest_train": 99.85,
    "highest_train_std": 0.13,
    "highest_valid": 96.97,
    "highest_valid_std": 0.35,
    "highest_in_test": 97.08,
    "highest_in_test_std": 0.22,
    "final_train": 99.82,
    "final_train_std": 0.16,
    "final_in_test": 96.97,
    "final_in_test_std": 0.23,
    "highest_ood_test_1": 89.2,
    "highest_ood_test_1_std": 0.19,
    "final_ood_test_1": 86.71,
    "final_ood_test_1_std": 0.83,
    "last_final_ood_test": 86.71
  },
  {
    "index": 2,
    "dataset": "pubmed",
    "backbone": "gat",
    "stage": "stage1",
    "result_name": "pubmed_gat_frontdoor_stage1_lr0.01_weight_decay5e-05_dropout0.1_hidden_channels32_K3",
    "log_file": "search_logs_frontdoor/pubmed/gat/stage1/002_pubmed_gat_frontdoor_stage1_lr0.01_weight_decay5e-05_dropout0.1_hidden_channels32_K3.log",
    "command": "python main_frontdoor.py --dataset pubmed --backbone_type gat --store_result --epochs 500 --runs 2 --num_layers 2 --device 1 --combine_result --lr 0.01 --weight_decay 5e-05 --dropout 0.1 --hidden_channels 32 --K 3 --result_name pubmed_gat_frontdoor_stage1_lr0.01_weight_decay5e-05_dropout0.1_hidden_channels32_K3",
    "return_code": 0,
    "elapsed_seconds": 433.05,
    "lr": 0.01,
    "weight_decay": 5e-05,
    "dropout": 0.1,
    "hidden_channels": 32,
    "K": 3,
    "highest_train": 99.84,
    "highest_train_std": 0.18,
    "highest_valid": 96.86,
    "highest_valid_std": 0.48,
    "highest_in_test": 96.98,
    "highest_in_test_std": 0.59,
    "final_train": 99.79,
    "final_train_std": 0.23,
    "final_in_test": 96.81,
    "final_in_test_std": 0.47,
    "highest_ood_test_1": 88.65,
    "highest_ood_test_1_std": 0.12,
    "final_ood_test_1": 85.73,
    "final_ood_test_1_std": 2.52,
    "last_final_ood_test": 85.73
  },
  {
    "index": 3,
    "dataset": "pubmed",
    "backbone": "gat",
    "stage": "stage1",
    "result_name": "pubmed_gat_frontdoor_stage1_lr0.01_weight_decay5e-05_dropout0.1_hidden_channels64_K2",
    "log_file": "search_logs_frontdoor/pubmed/gat/stage1/003_pubmed_gat_frontdoor_stage1_lr0.01_weight_decay5e-05_dropout0.1_hidden_channels64_K2.log",
    "command": "python main_frontdoor.py --dataset pubmed --backbone_type gat --store_result --epochs 500 --runs 2 --num_layers 2 --device 1 --combine_result --lr 0.01 --weight_decay 5e-05 --dropout 0.1 --hidden_channels 64 --K 2 --result_name pubmed_gat_frontdoor_stage1_lr0.01_weight_decay5e-05_dropout0.1_hidden_channels64_K2",
    "return_code": 0,
    "elapsed_seconds": 486.61,
    "lr": 0.01,
    "weight_decay": 5e-05,
    "dropout": 0.1,
    "hidden_channels": 64,
    "K": 2,
    "highest_train": 100.0,
    "highest_train_std": 0.0,
    "highest_valid": 97.48,
    "highest_valid_std": 0.08,
    "highest_in_test": 97.37,
    "highest_in_test_std": 0.18,
    "final_train": 99.99,
    "final_train_std": 0.0,
    "final_in_test": 97.23,
    "final_in_test_std": 0.22,
    "highest_ood_test_1": 91.72,
    "highest_ood_test_1_std": 1.09,
    "final_ood_test_1": 86.69,
    "final_ood_test_1_std": 1.26,
    "last_final_ood_test": 86.69
  },
  {
    "index": 4,
    "dataset": "pubmed",
    "backbone": "gat",
    "stage": "stage1",
    "result_name": "pubmed_gat_frontdoor_stage1_lr0.01_weight_decay5e-05_dropout0.1_hidden_channels64_K3",
    "log_file": "search_logs_frontdoor/pubmed/gat/stage1/004_pubmed_gat_frontdoor_stage1_lr0.01_weight_decay5e-05_dropout0.1_hidden_channels64_K3.log",
    "command": "python main_frontdoor.py --dataset pubmed --backbone_type gat --store_result --epochs 500 --runs 2 --num_layers 2 --device 1 --combine_result --lr 0.01 --weight_decay 5e-05 --dropout 0.1 --hidden_channels 64 --K 3 --result_name pubmed_gat_frontdoor_stage1_lr0.01_weight_decay5e-05_dropout0.1_hidden_channels64_K3",
    "return_code": 0,
    "elapsed_seconds": 435.78,
    "lr": 0.01,
    "weight_decay": 5e-05,
    "dropout": 0.1,
    "hidden_channels": 64,
    "K": 3,
    "highest_train": 99.99,
    "highest_train_std": 0.0,
    "highest_valid": 97.38,
    "highest_valid_std": 0.24,
    "highest_in_test": 97.39,
    "highest_in_test_std": 0.21,
    "final_train": 99.99,
    "final_train_std": 0.01,
    "final_in_test": 97.21,
    "final_in_test_std": 0.36,
    "highest_ood_test_1": 91.22,
    "highest_ood_test_1_std": 1.42,
    "final_ood_test_1": 86.45,
    "final_ood_test_1_std": 0.98,
    "last_final_ood_test": 86.45
  },
  {
    "index": 5,
    "dataset": "pubmed",
    "backbone": "gat",
    "stage": "stage1",
    "result_name": "pubmed_gat_frontdoor_stage1_lr0.01_weight_decay5e-05_dropout0.2_hidden_channels32_K2",
    "log_file": "search_logs_frontdoor/pubmed/gat/stage1/005_pubmed_gat_frontdoor_stage1_lr0.01_weight_decay5e-05_dropout0.2_hidden_channels32_K2.log",
    "command": "python main_frontdoor.py --dataset pubmed --backbone_type gat --store_result --epochs 500 --runs 2 --num_layers 2 --device 1 --combine_result --lr 0.01 --weight_decay 5e-05 --dropout 0.2 --hidden_channels 32 --K 2 --result_name pubmed_gat_frontdoor_stage1_lr0.01_weight_decay5e-05_dropout0.2_hidden_channels32_K2",
    "return_code": 0,
    "elapsed_seconds": 375.79,
    "lr": 0.01,
    "weight_decay": 5e-05,
    "dropout": 0.2,
    "hidden_channels": 32,
    "K": 2,
    "highest_train": 98.94,
    "highest_train_std": 0.21,
    "highest_valid": 96.1,
    "highest_valid_std": 0.31,
    "highest_in_test": 95.94,
    "highest_in_test_std": 0.33,
    "final_train": 98.85,
    "final_train_std": 0.21,
    "final_in_test": 95.87,
    "final_in_test_std": 0.44,
    "highest_ood_test_1": 88.89,
    "highest_ood_test_1_std": 0.79,
    "final_ood_test_1": 86.43,
    "final_ood_test_1_std": 0.42,
    "last_final_ood_test": 86.43
  },
  {
    "index": 6,
    "dataset": "pubmed",
    "backbone": "gat",
    "stage": "stage1",
    "result_name": "pubmed_gat_frontdoor_stage1_lr0.01_weight_decay5e-05_dropout0.2_hidden_channels32_K3",
    "log_file": "search_logs_frontdoor/pubmed/gat/stage1/006_pubmed_gat_frontdoor_stage1_lr0.01_weight_decay5e-05_dropout0.2_hidden_channels32_K3.log",
    "command": "python main_frontdoor.py --dataset pubmed --backbone_type gat --store_result --epochs 500 --runs 2 --num_layers 2 --device 1 --combine_result --lr 0.01 --weight_decay 5e-05 --dropout 0.2 --hidden_channels 32 --K 3 --result_name pubmed_gat_frontdoor_stage1_lr0.01_weight_decay5e-05_dropout0.2_hidden_channels32_K3",
    "return_code": 0,
    "elapsed_seconds": 439.13,
    "lr": 0.01,
    "weight_decay": 5e-05,
    "dropout": 0.2,
    "hidden_channels": 32,
    "K": 3,
    "highest_train": 98.98,
    "highest_train_std": 0.3,
    "highest_valid": 96.16,
    "highest_valid_std": 0.37,
    "highest_in_test": 96.06,
    "highest_in_test_std": 0.38,
    "final_train": 98.92,
    "final_train_std": 0.31,
    "final_in_test": 96.03,
    "final_in_test_std": 0.33,
    "highest_ood_test_1": 88.57,
    "highest_ood_test_1_std": 1.1,
    "final_ood_test_1": 86.83,
    "final_ood_test_1_std": 1.66,
    "last_final_ood_test": 86.83
  },
  {
    "index": 7,
    "dataset": "pubmed",
    "backbone": "gat",
    "stage": "stage1",
    "result_name": "pubmed_gat_frontdoor_stage1_lr0.01_weight_decay5e-05_dropout0.2_hidden_channels64_K2",
    "log_file": "search_logs_frontdoor/pubmed/gat/stage1/007_pubmed_gat_frontdoor_stage1_lr0.01_weight_decay5e-05_dropout0.2_hidden_channels64_K2.log",
    "command": "python main_frontdoor.py --dataset pubmed --backbone_type gat --store_result --epochs 500 --runs 2 --num_layers 2 --device 1 --combine_result --lr 0.01 --weight_decay 5e-05 --dropout 0.2 --hidden_channels 64 --K 2 --result_name pubmed_gat_frontdoor_stage1_lr0.01_weight_decay5e-05_dropout0.2_hidden_channels64_K2",
    "return_code": 0,
    "elapsed_seconds": 366.58,
    "lr": 0.01,
    "weight_decay": 5e-05,
    "dropout": 0.2,
    "hidden_channels": 64,
    "K": 2,
    "highest_train": 99.84,
    "highest_train_std": 0.02,
    "highest_valid": 97.16,
    "highest_valid_std": 0.24,
    "highest_in_test": 97.08,
    "highest_in_test_std": 0.19,
    "final_train": 99.82,
    "final_train_std": 0.0,
    "final_in_test": 96.93,
    "final_in_test_std": 0.04,
    "highest_ood_test_1": 93.15,
    "highest_ood_test_1_std": 0.11,
    "final_ood_test_1": 89.57,
    "final_ood_test_1_std": 0.88,
    "last_final_ood_test": 89.57
  },
  {
    "index": 8,
    "dataset": "pubmed",
    "backbone": "gat",
    "stage": "stage1",
    "result_name": "pubmed_gat_frontdoor_stage1_lr0.01_weight_decay5e-05_dropout0.2_hidden_channels64_K3",
    "log_file": "search_logs_frontdoor/pubmed/gat/stage1/008_pubmed_gat_frontdoor_stage1_lr0.01_weight_decay5e-05_dropout0.2_hidden_channels64_K3.log",
    "command": "python main_frontdoor.py --dataset pubmed --backbone_type gat --store_result --epochs 500 --runs 2 --num_layers 2 --device 1 --combine_result --lr 0.01 --weight_decay 5e-05 --dropout 0.2 --hidden_channels 64 --K 3 --result_name pubmed_gat_frontdoor_stage1_lr0.01_weight_decay5e-05_dropout0.2_hidden_channels64_K3",
    "return_code": 0,
    "elapsed_seconds": 393.07,
    "lr": 0.01,
    "weight_decay": 5e-05,
    "dropout": 0.2,
    "hidden_channels": 64,
    "K": 3,
    "highest_train": 99.83,
    "highest_train_std": 0.02,
    "highest_valid": 97.08,
    "highest_valid_std": 0.18,
    "highest_in_test": 97.03,
    "highest_in_test_std": 0.25,
    "final_train": 99.82,
    "final_train_std": 0.0,
    "final_in_test": 96.97,
    "final_in_test_std": 0.16,
    "highest_ood_test_1": 93.23,
    "highest_ood_test_1_std": 0.28,
    "final_ood_test_1": 89.87,
    "final_ood_test_1_std": 0.53,
    "last_final_ood_test": 89.87
  },
  {
    "index": 9,
    "dataset": "pubmed",
    "backbone": "gat",
    "stage": "stage1",
    "result_name": "pubmed_gat_frontdoor_stage1_lr0.005_weight_decay5e-05_dropout0.1_hidden_channels32_K2",
    "log_file": "search_logs_frontdoor/pubmed/gat/stage1/009_pubmed_gat_frontdoor_stage1_lr0.005_weight_decay5e-05_dropout0.1_hidden_channels32_K2.log",
    "command": "python main_frontdoor.py --dataset pubmed --backbone_type gat --store_result --epochs 500 --runs 2 --num_layers 2 --device 1 --combine_result --lr 0.005 --weight_decay 5e-05 --dropout 0.1 --hidden_channels 32 --K 2 --result_name pubmed_gat_frontdoor_stage1_lr0.005_weight_decay5e-05_dropout0.1_hidden_channels32_K2",
    "return_code": 0,
    "elapsed_seconds": 482.22,
    "lr": 0.005,
    "weight_decay": 5e-05,
    "dropout": 0.1,
    "hidden_channels": 32,
    "K": 2,
    "highest_train": 99.9,
    "highest_train_std": 0.06,
    "highest_valid": 97.36,
    "highest_valid_std": 0.39,
    "highest_in_test": 97.21,
    "highest_in_test_std": 0.31,
    "final_train": 99.88,
    "final_train_std": 0.07,
    "final_in_test": 97.16,
    "final_in_test_std": 0.23,
    "highest_ood_test_1": 88.64,
    "highest_ood_test_1_std": 1.99,
    "final_ood_test_1": 86.07,
    "final_ood_test_1_std": 3.94,
    "last_final_ood_test": 86.07
  },
  {
    "index": 10,
    "dataset": "pubmed",
    "backbone": "gat",
    "stage": "stage1",
    "result_name": "pubmed_gat_frontdoor_stage1_lr0.005_weight_decay5e-05_dropout0.1_hidden_channels32_K3",
    "log_file": "search_logs_frontdoor/pubmed/gat/stage1/010_pubmed_gat_frontdoor_stage1_lr0.005_weight_decay5e-05_dropout0.1_hidden_channels32_K3.log",
    "command": "python main_frontdoor.py --dataset pubmed --backbone_type gat --store_result --epochs 500 --runs 2 --num_layers 2 --device 1 --combine_result --lr 0.005 --weight_decay 5e-05 --dropout 0.1 --hidden_channels 32 --K 3 --result_name pubmed_gat_frontdoor_stage1_lr0.005_weight_decay5e-05_dropout0.1_hidden_channels32_K3",
    "return_code": 0,
    "elapsed_seconds": 436.61,
    "lr": 0.005,
    "weight_decay": 5e-05,
    "dropout": 0.1,
    "hidden_channels": 32,
    "K": 3,
    "highest_train": 99.92,
    "highest_train_std": 0.05,
    "highest_valid": 97.18,
    "highest_valid_std": 0.08,
    "highest_in_test": 97.26,
    "highest_in_test_std": 0.08,
    "final_train": 99.87,
    "final_train_std": 0.05,
    "final_in_test": 97.17,
    "final_in_test_std": 0.05,
    "highest_ood_test_1": 88.88,
    "highest_ood_test_1_std": 1.52,
    "final_ood_test_1": 87.09,
    "final_ood_test_1_std": 0.59,
    "last_final_ood_test": 87.09
  },
  {
    "index": 11,
    "dataset": "pubmed",
    "backbone": "gat",
    "stage": "stage1",
    "result_name": "pubmed_gat_frontdoor_stage1_lr0.005_weight_decay5e-05_dropout0.1_hidden_channels64_K2",
    "log_file": "search_logs_frontdoor/pubmed/gat/stage1/011_pubmed_gat_frontdoor_stage1_lr0.005_weight_decay5e-05_dropout0.1_hidden_channels64_K2.log",
    "command": "python main_frontdoor.py --dataset pubmed --backbone_type gat --store_result --epochs 500 --runs 2 --num_layers 2 --device 1 --combine_result --lr 0.005 --weight_decay 5e-05 --dropout 0.1 --hidden_channels 64 --K 2 --result_name pubmed_gat_frontdoor_stage1_lr0.005_weight_decay5e-05_dropout0.1_hidden_channels64_K2",
    "return_code": 0,
    "elapsed_seconds": 430.77,
    "lr": 0.005,
    "weight_decay": 5e-05,
    "dropout": 0.1,
    "hidden_channels": 64,
    "K": 2,
    "highest_train": 99.99,
    "highest_train_std": 0.0,
    "highest_valid": 97.56,
    "highest_valid_std": 0.09,
    "highest_in_test": 97.59,
    "highest_in_test_std": 0.01,
    "final_train": 99.99,
    "final_train_std": 0.0,
    "final_in_test": 97.45,
    "final_in_test_std": 0.03,
    "highest_ood_test_1": 90.91,
    "highest_ood_test_1_std": 0.48,
    "final_ood_test_1": 87.05,
    "final_ood_test_1_std": 0.17,
    "last_final_ood_test": 87.05
  },
  {
    "index": 12,
    "dataset": "pubmed",
    "backbone": "gat",
    "stage": "stage1",
    "result_name": "pubmed_gat_frontdoor_stage1_lr0.005_weight_decay5e-05_dropout0.1_hidden_channels64_K3",
    "log_file": "search_logs_frontdoor/pubmed/gat/stage1/012_pubmed_gat_frontdoor_stage1_lr0.005_weight_decay5e-05_dropout0.1_hidden_channels64_K3.log",
    "command": "python main_frontdoor.py --dataset pubmed --backbone_type gat --store_result --epochs 500 --runs 2 --num_layers 2 --device 1 --combine_result --lr 0.005 --weight_decay 5e-05 --dropout 0.1 --hidden_channels 64 --K 3 --result_name pubmed_gat_frontdoor_stage1_lr0.005_weight_decay5e-05_dropout0.1_hidden_channels64_K3",
    "return_code": 0,
    "elapsed_seconds": 441.53,
    "lr": 0.005,
    "weight_decay": 5e-05,
    "dropout": 0.1,
    "hidden_channels": 64,
    "K": 3,
    "highest_train": 99.99,
    "highest_train_std": 0.0,
    "highest_valid": 97.57,
    "highest_valid_std": 0.22,
    "highest_in_test": 97.56,
    "highest_in_test_std": 0.11,
    "final_train": 99.99,
    "final_train_std": 0.01,
    "final_in_test": 97.39,
    "final_in_test_std": 0.11,
    "highest_ood_test_1": 89.66,
    "highest_ood_test_1_std": 0.51,
    "final_ood_test_1": 87.29,
    "final_ood_test_1_std": 0.93,
    "last_final_ood_test": 87.29
  },
  {
    "index": 13,
    "dataset": "pubmed",
    "backbone": "gat",
    "stage": "stage1",
    "result_name": "pubmed_gat_frontdoor_stage1_lr0.005_weight_decay5e-05_dropout0.2_hidden_channels32_K2",
    "log_file": "search_logs_frontdoor/pubmed/gat/stage1/013_pubmed_gat_frontdoor_stage1_lr0.005_weight_decay5e-05_dropout0.2_hidden_channels32_K2.log",
    "command": "python main_frontdoor.py --dataset pubmed --backbone_type gat --store_result --epochs 500 --runs 2 --num_layers 2 --device 1 --combine_result --lr 0.005 --weight_decay 5e-05 --dropout 0.2 --hidden_channels 32 --K 2 --result_name pubmed_gat_frontdoor_stage1_lr0.005_weight_decay5e-05_dropout0.2_hidden_channels32_K2",
    "return_code": 0,
    "elapsed_seconds": 424.51,
    "lr": 0.005,
    "weight_decay": 5e-05,
    "dropout": 0.2,
    "hidden_channels": 32,
    "K": 2,
    "highest_train": 99.07,
    "highest_train_std": 0.23,
    "highest_valid": 96.4,
    "highest_valid_std": 0.29,
    "highest_in_test": 96.24,
    "highest_in_test_std": 0.19,
    "final_train": 99.03,
    "final_train_std": 0.22,
    "final_in_test": 96.18,
    "final_in_test_std": 0.26,
    "highest_ood_test_1": 89.14,
    "highest_ood_test_1_std": 1.74,
    "final_ood_test_1": 88.38,
    "final_ood_test_1_std": 1.39,
    "last_final_ood_test": 88.38
  },
  {
    "index": 14,
    "dataset": "pubmed",
    "backbone": "gat",
    "stage": "stage1",
    "result_name": "pubmed_gat_frontdoor_stage1_lr0.005_weight_decay5e-05_dropout0.2_hidden_channels32_K3",
    "log_file": "search_logs_frontdoor/pubmed/gat/stage1/014_pubmed_gat_frontdoor_stage1_lr0.005_weight_decay5e-05_dropout0.2_hidden_channels32_K3.log",
    "command": "python main_frontdoor.py --dataset pubmed --backbone_type gat --store_result --epochs 500 --runs 2 --num_layers 2 --device 1 --combine_result --lr 0.005 --weight_decay 5e-05 --dropout 0.2 --hidden_channels 32 --K 3 --result_name pubmed_gat_frontdoor_stage1_lr0.005_weight_decay5e-05_dropout0.2_hidden_channels32_K3",
    "return_code": 0,
    "elapsed_seconds": 407.14,
    "lr": 0.005,
    "weight_decay": 5e-05,
    "dropout": 0.2,
    "hidden_channels": 32,
    "K": 3,
    "highest_train": 99.13,
    "highest_train_std": 0.23,
    "highest_valid": 96.46,
    "highest_valid_std": 0.2,
    "highest_in_test": 96.4,
    "highest_in_test_std": 0.24,
    "final_train": 99.1,
    "final_train_std": 0.21,
    "final_in_test": 96.32,
    "final_in_test_std": 0.22,
    "highest_ood_test_1": 89.62,
    "highest_ood_test_1_std": 0.65,
    "final_ood_test_1": 88.08,
    "final_ood_test_1_std": 0.32,
    "last_final_ood_test": 88.08
  },
  {
    "index": 15,
    "dataset": "pubmed",
    "backbone": "gat",
    "stage": "stage1",
    "result_name": "pubmed_gat_frontdoor_stage1_lr0.005_weight_decay5e-05_dropout0.2_hidden_channels64_K2",
    "log_file": "search_logs_frontdoor/pubmed/gat/stage1/015_pubmed_gat_frontdoor_stage1_lr0.005_weight_decay5e-05_dropout0.2_hidden_channels64_K2.log",
    "command": "python main_frontdoor.py --dataset pubmed --backbone_type gat --store_result --epochs 500 --runs 2 --num_layers 2 --device 1 --combine_result --lr 0.005 --weight_decay 5e-05 --dropout 0.2 --hidden_channels 64 --K 2 --result_name pubmed_gat_frontdoor_stage1_lr0.005_weight_decay5e-05_dropout0.2_hidden_channels64_K2",
    "return_code": 0,
    "elapsed_seconds": 430.78,
    "lr": 0.005,
    "weight_decay": 5e-05,
    "dropout": 0.2,
    "hidden_channels": 64,
    "K": 2,
    "highest_train": 99.91,
    "highest_train_std": 0.05,
    "highest_valid": 97.27,
    "highest_valid_std": 0.16,
    "highest_in_test": 97.25,
    "highest_in_test_std": 0.23,
    "final_train": 99.89,
    "final_train_std": 0.06,
    "final_in_test": 97.24,
    "final_in_test_std": 0.21,
    "highest_ood_test_1": 92.19,
    "highest_ood_test_1_std": 0.84,
    "final_ood_test_1": 90.86,
    "final_ood_test_1_std": 0.97,
    "last_final_ood_test": 90.86
  },
  {
    "index": 16,
    "dataset": "pubmed",
    "backbone": "gat",
    "stage": "stage1",
    "result_name": "pubmed_gat_frontdoor_stage1_lr0.005_weight_decay5e-05_dropout0.2_hidden_channels64_K3",
    "log_file": "search_logs_frontdoor/pubmed/gat/stage1/016_pubmed_gat_frontdoor_stage1_lr0.005_weight_decay5e-05_dropout0.2_hidden_channels64_K3.log",
    "command": "python main_frontdoor.py --dataset pubmed --backbone_type gat --store_result --epochs 500 --runs 2 --num_layers 2 --device 1 --combine_result --lr 0.005 --weight_decay 5e-05 --dropout 0.2 --hidden_channels 64 --K 3 --result_name pubmed_gat_frontdoor_stage1_lr0.005_weight_decay5e-05_dropout0.2_hidden_channels64_K3",
    "return_code": 0,
    "elapsed_seconds": 412.6,
    "lr": 0.005,
    "weight_decay": 5e-05,
    "dropout": 0.2,
    "hidden_channels": 64,
    "K": 3,
    "highest_train": 99.92,
    "highest_train_std": 0.04,
    "highest_valid": 97.27,
    "highest_valid_std": 0.19,
    "highest_in_test": 97.18,
    "highest_in_test_std": 0.08,
    "final_train": 99.89,
    "final_train_std": 0.03,
    "final_in_test": 97.12,
    "final_in_test_std": 0.03,
    "highest_ood_test_1": 92.69,
    "highest_ood_test_1_std": 0.16,
    "final_ood_test_1": 89.82,
    "final_ood_test_1_std": 0.63,
    "last_final_ood_test": 89.82
  }
]